terminal_markup/__init__.py
terminal_markup/__main__.py
terminal_markup/cli.py
terminal_markup/escape_sequence.py
terminal_markup/markup.py
terminal_markup/renderer.py
terminal_markup/utils/color.py
terminal_markup/utils/constant.py
terminal_markup/utils/enum.py
terminal_markup-0.2.8.dist-info/LICENSE
terminal_markup-0.2.8.dist-info/METADATA
terminal_markup-0.2.8.dist-info/WHEEL
terminal_markup-0.2.8.dist-info/entry_points.txt
terminal_markup-0.2.8.dist-info/RECORD
