Metadata-Version: 2.1
Name: terminal-markup
Version: 0.2.8
Summary: Render Markup to Terminal
Home-page: https://github.com/s3rgeym/terminal-markup
License: MIT
Author: Sergey M
Requires-Python: >=3.11,<4.0
Classifier: License :: OSI Approved :: MIT License
Classifier: Programming Language :: Python :: 3
Classifier: Programming Language :: Python :: 3.11
Project-URL: Repository, https://github.com/s3rgeym/terminal-markup
